MANIFEST.in
README.rst
setup.py
uvtor/__init__.py
uvtor/__main__.py
uvtor.egg-info/PKG-INFO
uvtor.egg-info/SOURCES.txt
uvtor.egg-info/dependency_links.txt
uvtor.egg-info/entry_points.txt
uvtor.egg-info/requires.txt
uvtor.egg-info/top_level.txt
uvtor/_templates/app_template/__init__.py.tpl
uvtor/_templates/app_template/handlers/__init__.py.tpl
uvtor/_templates/app_template/handlers/v0/__init__.py.tpl
uvtor/_templates/app_template/handlers/v0/main.py.tpl
uvtor/_templates/app_template/routes/v0/__init__.py.tpl
uvtor/_templates/project_template/.uvtor.tpl
uvtor/_templates/project_template/__init__.py.tpl
uvtor/_templates/project_template/settings.py.tpl
uvtor/_templates/project_template/apps/__init__.py.tpl
uvtor/_templates/project_template/models/__init__.py.tpl
uvtor/_templates/project_template/tasks/__init__.py.tpl
uvtor/_templates/project_template/tests/__init__.py
uvtor/_templates/test_template/__init__.py.tpl
uvtor/_templates/test_template/v0.py.tpl
uvtor/bin/uvtor.py
uvtor/conf/__init__.py
uvtor/core/__init__.py
uvtor/core/exceptions.py
uvtor/core/handlers.py
uvtor/core/response.py
uvtor/core/tests.py
uvtor/core/cache/__init__.py
uvtor/core/decorators/__init__.py
uvtor/core/decorators/api.py
uvtor/core/decorators/design.py
uvtor/core/decorators/user.py
uvtor/core/mail/__init__.py
uvtor/core/management/__init__.py
uvtor/core/management/base.py
uvtor/core/management/commands/__init__.py
uvtor/core/management/commands/createapp.py
uvtor/core/management/commands/createdb.py
uvtor/core/management/commands/createproj.py
uvtor/core/management/commands/dropdb.py
uvtor/core/management/commands/getconfig.py
uvtor/core/management/commands/makemigrations.py
uvtor/core/management/commands/migrate.py
uvtor/core/management/commands/newmigration.py
uvtor/core/management/commands/removeapp.py
uvtor/core/management/commands/runapp.py
uvtor/core/management/commands/runtests.py
uvtor/db/__init__.py
uvtor/db/migrations/__init__.py
uvtor/db/migrations/__main__.py
uvtor/db/migrations/auto.py
uvtor/db/migrations/cli.py
uvtor/db/migrations/compat.py
uvtor/db/migrations/migrator.py
uvtor/db/migrations/router.py
uvtor/db/migrations/template.txt
