Metadata-Version: 2.1
Name: uvtor
Version: 0.0.18
Summary: A project management tools.
Home-page: UNKNOWN
Author: Jerevia
Author-email: trilliondawn@gmail.com
License: MIT
Keywords: uvtor tornado webframework web framework
Platform: UNKNOWN
Classifier: Development Status :: 4 - Beta
Classifier: Intended Audience :: Developers
Classifier: Topic :: Software Development :: Build Tools
Classifier: License :: OSI Approved :: MIT License
Classifier: Programming Language :: Python :: 3.5
Classifier: Programming Language :: Python :: 3.6
Requires-Python: >=3.6
Provides-Extra: test
Provides-Extra: dev
